pytecgg-0.3.0.dist-info/METADATA
pytecgg-0.3.0.dist-info/WHEEL
pytecgg-0.3.0.dist-info/licenses/LICENSE
pytecgg/__init__.py
pytecgg/linear_combinations/__init__.py
pytecgg/linear_combinations/constants.py
pytecgg/linear_combinations/cs_lol_detection.py
pytecgg/linear_combinations/gflc.py
pytecgg/linear_combinations/iflc.py
pytecgg/linear_combinations/lc_calculation.py
pytecgg/linear_combinations/mw.py
pytecgg/parsing/__init__.py
pytecgg/pytecgg.cp311-win32.pyd
pytecgg/satellites/__init__.py
pytecgg/satellites/constants.py
pytecgg/satellites/ephemeris.py
pytecgg/satellites/glonass.py
pytecgg/satellites/ipp.py
pytecgg/satellites/kepler.py
pytecgg/satellites/positions.py
pytecgg/tec_calibration/__init__.py
pytecgg/tec_calibration/arcs.py
pytecgg-0.3.0.dist-info/RECORD
