Metadata-Version: 2.4
Name: pytecgg
Version: 0.3.0
Classifier: Programming Language :: Python :: 3
Classifier: License :: OSI Approved :: GNU General Public License v3 or later (GPLv3+)
Classifier: Operating System :: OS Independent
Classifier: Development Status :: 4 - Beta
Requires-Dist: polars>=1.20.0
Requires-Dist: numpy>=2.0.0
Requires-Dist: scipy>=1.15
Requires-Dist: pymap3d>=3.2
Requires-Dist: tzdata>=2025.2
License-File: LICENSE
Summary: Total Electron Content (TEC) reconstruction with GNSS data – a Python package with a Rust core
Author-email: Vincenzo Ventriglia <vincenzo.ventriglia@outlook.com>
License: GPL-3.0-or-later
Requires-Python: >=3.11, <3.14
